getinstance-0.7.dist-info/METADATA
getinstance-0.7.dist-info/WHEEL
getinstance-0.7.dist-info/entry_points.txt
getinstance.py
getinstance-0.7.dist-info/RECORD
